{"cell_type":{"c704ae23":"code","fcb21436":"code","fc26ec29":"code","d18e7cd2":"code","dfa69942":"code","cec3b11b":"code","cfc2d74c":"code","15506ee9":"code","388e2b91":"code","c52dd385":"code","68e57e59":"code","9b877603":"code","abb9f18c":"code","03c9ef77":"code","4a0b2f29":"code","a5256788":"code","0f0dcca1":"code","72be68d5":"code","9dfbe2b9":"code","c8d29de3":"code","67c8a517":"code","30b93211":"code","313a126b":"code","74021987":"code","115d66fc":"code","0270e7a1":"code","07a3e1cf":"code","d43da271":"code","e11083ff":"code","36dcc430":"code","dfe77526":"code","f6e7cc16":"code","7b075560":"code","95b272d4":"code","a8b45450":"code","140ce2c1":"code","716ff268":"code","698a2436":"code","f94ff867":"code","e5c18ff8":"code","cb1cc244":"markdown","a2302341":"markdown","f3364467":"markdown","c643623a":"markdown","3b9a8f25":"markdown","329fb9ab":"markdown","e5ac6e36":"markdown","f99789db":"markdown","57ec6ee7":"markdown","a8a08602":"markdown","4f0bd15e":"markdown"},"source":{"c704ae23":"\nimport numpy as np \nimport pandas as pd \nimport matplotlib.pyplot as plt\nimport seaborn as sns\n%matplotlib inline\nfrom sklearn.preprocessing import StandardScaler \nfrom sklearn.linear_model  import LinearRegression,Ridge,Lasso,RidgeCV, LassoCV, ElasticNet, ElasticNetCV\nfrom sklearn.model_selection import train_test_split\n\nimport os\nfor dirname, _, filenames in os.walk('\/kaggle\/input'):\n    for filename in filenames:\n        print(os.path.join(dirname, filename))\n","fcb21436":"df=pd.read_csv('\/kaggle\/input\/vehicle-dataset-from-cardekho\/car data.csv')\ndf.head()","fc26ec29":"df.shape","d18e7cd2":"df.info()","dfa69942":"df['Owner'].unique()","cec3b11b":"df['Number_of_Year']=2020-df['Year'] #age of the car","cfc2d74c":"df.head()","15506ee9":"sns.pairplot(df)","388e2b91":"sns.regplot('Year','Selling_Price',data=df)","c52dd385":"sns.regplot('Number_of_Year','Selling_Price',data=df)","68e57e59":"ax = sns.barplot(x=\"Seller_Type\", y=\"Selling_Price\", data=df)","9b877603":"ax = sns.barplot(x=\"Fuel_Type\", y=\"Selling_Price\", data=df)","abb9f18c":"ax = sns.barplot(x=\"Transmission\", y=\"Selling_Price\", data=df)","03c9ef77":"ax = sns.barplot(x=\"Owner\", y=\"Selling_Price\", data=df)","4a0b2f29":"sns.regplot('Selling_Price','Kms_Driven',data=df)","a5256788":"df.columns","0f0dcca1":"final=df[['Selling_Price', 'Present_Price', 'Kms_Driven',\n       'Fuel_Type', 'Seller_Type', 'Transmission', 'Owner', 'Number_of_Year']]\nfinal_df=pd.get_dummies(final,drop_first=True)","72be68d5":"final_df.head()","9dfbe2b9":"plt.figure(figsize=(10,10))\nax = sns.heatmap(final_df.corr(),annot=True)","c8d29de3":"y=df.Selling_Price\nx=final_df.drop(['Selling_Price'],axis=1)","67c8a517":"x.head()","30b93211":"y.head()","313a126b":"X_train, X_test, y_train, y_test = train_test_split(x, y, test_size=0.25, random_state=0)","74021987":"reg=LinearRegression()\nreg.fit(X_train,y_train)","115d66fc":"print(reg.intercept_)\nprint(reg.coef_)","0270e7a1":"from sklearn.metrics import mean_squared_error\nmean_squared_error(y_true=y_train, y_pred=reg.predict(X_train))","07a3e1cf":"from sklearn.metrics import r2_score\nr2_score(y_true=y_train, y_pred=reg.predict(X_train))","d43da271":"lasscv = LassoCV(alphas = None,cv =10, max_iter = 100000, normalize = True)\nlasscv.fit(X_train, y_train)","e11083ff":"alpha = lasscv.alpha_\nalpha","36dcc430":"lasso_reg = Lasso(alpha)\nlasso_reg.fit(X_train, y_train)","dfe77526":"lasso_reg.score(X_test, y_test)","f6e7cc16":"alphas = np.random.uniform(low=0, high=10, size=(50,))\nridgecv = RidgeCV(alphas = alphas,cv=10,normalize = True)\nridgecv.fit(X_train, y_train)","7b075560":"ridgecv.alpha_","95b272d4":"ridge_model = Ridge(alpha=ridgecv.alpha_)\nridge_model.fit(X_train, y_train)","a8b45450":"ridge_model.score(X_test, y_test)","140ce2c1":"elasticCV = ElasticNetCV(alphas = None, cv =10)\n\nelasticCV.fit(X_train, y_train)","716ff268":"elasticCV.alpha_","698a2436":"elasticCV.l1_ratio","f94ff867":"elasticnet_reg = ElasticNet(alpha = elasticCV.alpha_,l1_ratio=0.5)\nelasticnet_reg.fit(X_train, y_train)","e5c18ff8":"elasticnet_reg.score(X_test, y_test)","cb1cc244":"**Automatic cars have higher selling price**","a2302341":"# Lasso Regression","f3364467":"**No null values**","c643623a":"# Exploratory Data Analysis","3b9a8f25":"# Ridge Regression","329fb9ab":"**Diesel cars are most expensive**","e5ac6e36":"# Elastic net","f99789db":"**Cars sold by the dealers have higher selling price**","57ec6ee7":"**A newer car is more expensive**","a8a08602":"**Older the car, lower the selling price.**","4f0bd15e":"# Linear Regression"}}