{"cell_type":{"f5e2362e":"code","a06515f9":"code","1149a9fa":"code","d5593c70":"code","3469e249":"code","2e546fbf":"code","a203e0be":"code","b9c8a048":"code","ffff624c":"code","5404161e":"code","61fbb524":"code","2ad0b810":"code","9e9e390e":"code","b5afbda5":"code","d84e76e4":"code","00b283dd":"code","f62ebf55":"code","2adb73ab":"code","f5dc0ff3":"code","047bf04d":"code","7b3596cd":"code","f86bd4d0":"code","8485cecd":"code","b6f5f58d":"code","9ed26f7e":"code","961411f9":"code","1d24b6e4":"code","979c83b7":"code","32d41a7f":"code","8300d20a":"code","011a6fda":"code","b6421947":"code","6be0bd04":"code","a9a2435b":"code","70bc228e":"code","be1d88a0":"code","fef8fd7b":"code","be138355":"code","05e0786c":"code","53dffd1c":"code","4a5cc3ff":"code","6e85811a":"code","20e3ebd3":"code","d230d82c":"code","c4a94f06":"code","97f3e174":"code","c88c967d":"code","7c73b510":"code","1aa3992f":"code","f2b37cba":"code","187aa17f":"code","c5c6421f":"code","5cd642e9":"code","ddc298bb":"code","e4c06835":"code","0c604323":"code","f8fa2dd2":"code","892bd614":"code","6bccd4fc":"code","769b7d3e":"code","1ba20124":"markdown","e89c3fbe":"markdown","8b72d4a3":"markdown","9ace1ecc":"markdown","38276755":"markdown","aa282b18":"markdown","1606d132":"markdown","b8707f6b":"markdown","f2ed1c58":"markdown","0b87e517":"markdown","40ef7d3e":"markdown","52fca9d3":"markdown","ee12258a":"markdown","db7625a2":"markdown","c312d49f":"markdown","173d5317":"markdown","c138c2fc":"markdown","de98cab2":"markdown","15499cd6":"markdown","c159982b":"markdown","347632d6":"markdown","23a1e518":"markdown","6b26cc74":"markdown","a46bf927":"markdown","a4c5cf3b":"markdown","271256c9":"markdown","e5f0f858":"markdown","c3c01c8c":"markdown","25aed099":"markdown","bdf4d129":"markdown","bf3b614f":"markdown","7608cb7c":"markdown","e4c497a3":"markdown","f7a2b98f":"markdown","4d493cf8":"markdown","1d42a13b":"markdown","50c8ceef":"markdown","f950fecb":"markdown","3a5bfb4a":"markdown","3514d4f0":"markdown","d79bea27":"markdown","479452fe":"markdown","302068e5":"markdown","72db5f4b":"markdown","6435213d":"markdown","c47faca3":"markdown","76a3686e":"markdown","d858721f":"markdown","640af54e":"markdown","7c64e60e":"markdown","720ea84b":"markdown","6a4e26aa":"markdown","a95eaac6":"markdown","013cccc3":"markdown","7f4cd141":"markdown","3c445e15":"markdown","a4e5f6b3":"markdown","85d4582d":"markdown","ddd59e13":"markdown","d84c4b1e":"markdown","bd909d76":"markdown","2bd1d9c7":"markdown","3620d980":"markdown","96c5b5d1":"markdown","17fcc73d":"markdown","47eea9b4":"markdown","f409f8ef":"markdown","58a71409":"markdown","b0d27ab6":"markdown","5b3d6f7a":"markdown","8d33fcc7":"markdown","59cddff3":"markdown","19eb0e5d":"markdown","daeb3d5c":"markdown","ba347fc9":"markdown","bd342a49":"markdown","3c169cb1":"markdown","603f39cc":"markdown","ff7af586":"markdown","d6e06e9b":"markdown","6cfab2e2":"markdown","a990d1b3":"markdown","198829de":"markdown"},"source":{"f5e2362e":"import pandas as pd\nimport numpy as np\nimport matplotlib.pyplot as plt\nimport seaborn as sns\nimport warnings\nimport pandas_profiling as ppf\n#Supress warnings\nwarnings.filterwarnings('ignore') ","a06515f9":"cgf_data=pd.read_csv(\"..\/input\/cardiogoodfitness\/CardioGoodFitness.csv\")","1149a9fa":"cgf_data.head()","d5593c70":"cgf_data.tail()","3469e249":"cgf_data.shape","2e546fbf":"cgf_data.dtypes","a203e0be":"cgf_data.info()","b9c8a048":"cgf_data.columns","ffff624c":"cgf_data_back = cgf_data\n#Verify the backup\ncgf_data_back","5404161e":"cgf_data.isnull().sum()","61fbb524":"cgf_data.duplicated().sum()","2ad0b810":"cgf_data.describe()","9e9e390e":"cgf_data.describe(include ='all')","b5afbda5":"# Transpose the data for another view\ncgf_data.describe().T","d84e76e4":"cgf_data.Product.value_counts()","00b283dd":"cgf_data.Gender.value_counts()","f62ebf55":"cgf_data.MaritalStatus.value_counts()   ","2adb73ab":"cgf_data[cgf_data['Product'] == 'TM195'].describe().T","f5dc0ff3":"cgf_data[cgf_data['Product'] == 'TM498'].describe().T","047bf04d":"cgf_data[cgf_data['Product'] == 'TM798'].describe().T","7b3596cd":"# Historam for age\nplt.hist(cgf_data.Age, edgecolor = 'white')\nplt.title(\"Histogram view of Age\")\nplt.show()","f86bd4d0":"# Distribute data in Age groups\nbins = [20,25,30,35,40,45,50]\nplt.hist(cgf_data.Age,bins,edgecolor = 'white')\nplt.title(\"Categorical histogram of Age\")\nplt.show()","8485cecd":"# Distribute data in Age groups\nbins = [18,20,22,24,26,28,30,32,34]\nplt.hist(cgf_data.Age,bins,edgecolor = 'white')\nplt.title(\"Categorical histogram of Age\")\nplt.show()","b6f5f58d":"# Visualisation of income range\nsns.distplot(cgf_data.Income)\nplt.title(\"Distribution Plot of Income\")\nplt.show()","9ed26f7e":"# boxplot view of income\nsns.boxplot(cgf_data.Income)\nplt.title(\"Box plot Plot of Income\")\nplt.show()","961411f9":"# Number of records per gender and product model\nsns.countplot(cgf_data.Gender, hue=cgf_data.Product)\nplt.title('Gender based distribution')\nplt.show()","1d24b6e4":"# Number of records per model and per gender\nsns.countplot(cgf_data.Product, hue=cgf_data.Gender)\nplt.title('Gender based distribution')\nplt.show()","979c83b7":"#\u00a0Number\u00a0of\u00a0records per\u00a0model\u00a0and\u00a0per\u00a0Marital Status\nsns.countplot(cgf_data.Product, hue=cgf_data.MaritalStatus)\nplt.title('Marital Status based distribution')\nplt.show()","32d41a7f":"#\u00a0Number\u00a0of\u00a0records\u00a0per\u00a0model\u00a0and\u00a0per\u00a0Marital Status\nsns.countplot(cgf_data.MaritalStatus, hue=cgf_data.Product)\nplt.title('Marital Status based distribution')\nplt.show()","8300d20a":"#\u00a0Number\u00a0of\u00a0records based on usage per week\nsns.countplot(cgf_data.Usage)\nplt.title('Count based on Usage')\nplt.show()","011a6fda":"#\u00a0Number\u00a0of\u00a0records\u00a0per\u00a0model\u00a0and\u00a0for number of times of\u00a0Usage\nsns.countplot(cgf_data.Product, hue=cgf_data.Usage)\nplt.title('Usage based distribution')\nplt.show()","b6421947":"#\u00a0Number\u00a0of\u00a0records\u00a0per\u00a0model\u00a0and\u00a0per\u00a0Usage\nsns.countplot(cgf_data.Usage, hue=cgf_data.Product)\nplt.title('Usage based distribution')\nplt.show()","6be0bd04":"#\u00a0Number\u00a0of\u00a0records\u00a0per\u00a0Fitness\nsns.countplot(cgf_data.Fitness)\nplt.title('Count based on Self Acclaimed Fitness Levels')\nplt.show()","a9a2435b":"#\u00a0Number\u00a0of\u00a0records\u00a0per\u00a0model\u00a0and\u00a0for fitness rating\nsns.countplot(cgf_data.Product, hue=cgf_data.Fitness)\nplt.title('Distribution based on Fitness Levels')\nplt.show()","70bc228e":"#\u00a0Number\u00a0of\u00a0records\u00a0per\u00a0model\u00a0and\u00a0for fitness rating\nsns.countplot(cgf_data.Fitness, hue=cgf_data.Product)\nplt.title('Distribution based on Fitness Levels')\nplt.show()","be1d88a0":"# Distribution based on number of years of education\nsns.countplot(cgf_data.Education)\nplt.title(\"Count based on number of years of Education\")\nplt.show()","fef8fd7b":"# Number of records per model for customer segments based on the number of years of education\nsns.countplot(cgf_data.Education, hue=cgf_data.Product)\nplt.title('Distribution based on Education')\nplt.show()","be138355":"# Number of records per model for customer segments based on the number of years of education\nplt.figure(figsize=(10,5))\nsns.countplot(cgf_data.Product, hue=cgf_data.Education)\nplt.title('Distribution based on Education')\nplt.show()","05e0786c":"# Distribution plot of Miles with RUG and KDE\nsns.distplot(cgf_data.Miles, rug=True)\nplt.title('Count based on Miles')\nplt.show()","53dffd1c":"# Boxplot view of data based on miles\nsns.boxplot(cgf_data.Miles)\nplt.title(\"Boxplot of Miles\")\nplt.show()","4a5cc3ff":"# List the data where miles are greater than 180\ncgf_data[cgf_data['Miles'] > 180]","6e85811a":"cgf_data.groupby('Product')['Age'].mean()","20e3ebd3":"cgf_data.groupby('Product')['Income'].mean()","d230d82c":"cgf_data.groupby('Product')['Miles'].mean()","c4a94f06":"cgf_data.groupby('Product')['Education'].mean()","97f3e174":"sns.jointplot(x = 'Age' , y = 'Miles', data = cgf_data)\nplt.show()","c88c967d":"sns.jointplot(x = 'Age' , y = 'Income', data = cgf_data, color='red', kind ='hex')\nplt.show()","7c73b510":"sns.jointplot(x = 'Income' , y = 'Miles', data = cgf_data, color='orange', kind ='hex')\nplt.show()","1aa3992f":"sns.catplot(x = 'Gender' , y = 'Income', data = cgf_data)\nplt.show()","f2b37cba":"sns.catplot(x = 'Gender' , y = 'Miles', data = cgf_data, kind = 'violin')\nplt.show()","187aa17f":"sns.catplot(x = 'Gender' , y = 'Usage', data = cgf_data, kind = 'bar')\nplt.show()","c5c6421f":"sns.catplot(x = 'MaritalStatus' , y = 'Income', data = cgf_data, kind = 'box')\nplt.show()","5cd642e9":"sns.catplot(x = 'MaritalStatus' , y = 'Miles', data = cgf_data, kind = 'swarm')\nplt.show()","ddc298bb":"sns.catplot( x = \"Gender\", y = 'Income', hue = 'Product', col = 'MaritalStatus',data = cgf_data, kind = 'bar');","e4c06835":"sns.pointplot(x=cgf_data[\"Education\"],y=cgf_data[\"Income\"],hue=cgf_data['Product']) \nplt.show()","0c604323":"# Correlation of numerical values in dataset\ncgf_data.corr()","f8fa2dd2":"# Heatmap for the correlation of numerical values in dataset\nsns.heatmap(cgf_data.corr(), annot=True, vmin=-1, vmax = 1) \nplt.show()","892bd614":"sns.pairplot(cgf_data, hue='Product')\nplt.show()","6bccd4fc":"sns.pairplot(cgf_data, kind='kde')\nplt.show()","769b7d3e":"# Module : Fundamentals of AIML\n# Project: EDA - Cardio Good Fitness\n# Submitted by : Ritesh Sharma\n# Submission Date : 23 Jul 2021","1ba20124":"**Observations:** There are no missing values in the dataset","e89c3fbe":"**Observations:**\n\n1. There are two peaks shown by the income range of people\n2. Data is right skewed and shows outliers on the right\n3. Most Customers fall in range of USD 45,000 - USD 60,000\n4. Outliers are observed above USD 85,000","8b72d4a3":" **Observations:**\n\n1. Columns Product, Gender and Marital Status are of string datatype \n2. Columns Age, Education, Usage, Fitness, Income and Miles are of integer (numerical) datatype","9ace1ecc":"#### Count based on Gender","38276755":"**Observations:**\n\n1. Most customers use Treadmill at least 3 times per week\n2. TM195 is most popular amongst active customers\n3. Few customers using TM798 Model use the treadmill for 7 times in a week","aa282b18":"**Observations:**\n\n1. Most Customers using treadmill have 16 to 18 years of Education\n2. Customers with more than 20 years of education have only purchased TM798 Model\n3. TM798 is most preferred by the customer with 18 years of education","1606d132":"#### Examine the first 5 rows of the data","b8707f6b":"## Multivariate Analysis:","f2ed1c58":"## Univeriate Analysis:","0b87e517":"### Analysis of Miles based on Gender","40ef7d3e":"#### Average\u00a0Income\u00a0for\u00a0each\u00a0model","52fca9d3":"#### Understand data for Product Code TM798","ee12258a":"# Exploratory Data Analysis - Cardio Good Fitness\n Cardio Good Fitness is a retail store and this data is  of customers who purchased various treadmill models.\n ","db7625a2":"## Bivariate Analysis:","c312d49f":"**Observations:**\n\n1. Miles and Usage show high correlation\n2. Fitness and Miles show high correlation\n3. Education and Income show notable correlation\n4. Usage and Fitness show notable correlation\n5. Income and Usage show little correlation","173d5317":"**Observation:-**\n\n   1. Customers with higher education has higher income range\n   2. TM798 has higher income and higher education","c138c2fc":"### Analysis based on Miles planned per week","de98cab2":"### Analysis of Income based on Age","15499cd6":"#### Average\u00a0miles\u00a0per\u00a0model","c159982b":"**Observations:**\n\nThere is no definite correlation observed between Age and Miles","347632d6":"**Observations:** \n\n1. There are 107 Partnered Customers  \n2. There are 73 Single Customers. \n3. Partnered Customers are buying more treadmills compared to Single Customers","23a1e518":"### Analysis of Miles based on Age","6b26cc74":"#### Identify the missing values in dataset","a46bf927":"#### Check additional information on the dataframe","a4c5cf3b":"### Analysis based on Education","271256c9":"**Observations:**\n\n1. Partnered Customers have purchased treadmill more than Single Customers\n2. TM195 model is popular in both Marital Statuses\n","e5f0f858":" **Observations:** There are 180 observations of 9 columns in the dataset","c3c01c8c":"**Observations:** \n\n1. There are 76 female Customers  \n2. There are 104 male Customers \n3. Male Customers are buying more treadmills compared to Female Customers","25aed099":"#### Pairplot of all numerical values with clasification of Product","bdf4d129":"**Observations:**\n\n1. A total of 80 customers purchased TM195 model \n2. Average age of customer is 28.5 (Median: 26) (Range: 18 - 50)\n3. Data is right skewed.\n4. Average number of years of Education for customers is 15 (Median: 16)\n3. Customer wants to use the treadmill at least 3 times per week\n4. Customers are expected to run is 82.78 miles per week (Median: 85)\n5. Average income and median is approximately USD 46,000 ","bf3b614f":"**Observations:**\n\nMale Customers have higher income range, when compared to Female Customers","7608cb7c":"#### Identify the duplicate records","e4c497a3":"### Analysis based on Fitness Level","f7a2b98f":"**Observations:**\n\n1. Most customers have rated themselves at Level 3 of Fitness levels\n2. TM195 is most popular amongst customers at Level 3\n3. Almost all Customers at Fitness Level 5 use TM798 model","4d493cf8":"### Multicolumn catplot of Marital Status showing Gender based data compared to Income","1d42a13b":"### Pointplot showing sales based on Education and Income","50c8ceef":"#### Count based on model","f950fecb":"**Observations:**\n\nWith increase in Customer Income a slight increase is observed in Miles","3a5bfb4a":"### Load Dataset:","3514d4f0":"### Correlation between Numerical columns of dataset","d79bea27":"### Analysis of Income based on Marital Status","479452fe":"**Observations:** \n\n**A. AGE:**\n\n    1. Customers between 18 and 50 years of age are using treadmill\n    2. Average age is 28.78 years\n    3. As there is not much difference in mean and median, the skewness in data is minimal\n\n**B. INCOME:**\n\n    1. Customers with income range of USD 29,500 to USD 104,500 are using treadmill\n    2. Considering the difference between mean and median & mean being greater than median, the data is right skewed\n    3. Standard deviation is very high\n\n**C. MILES:**\n\n    1. Customers are expected to run between 21 to 360 miles per week\n    2. Considering the difference between mean and median & mean being greater than median, the data is right skewed\n    3. Standard deviation is very high","302068e5":"### Import required libraries:","72db5f4b":"#### Check the size of data","6435213d":"### Analysis of Miles based on Income","c47faca3":"### Analysis of Usage based on Gender","76a3686e":"**Observations:**\n\n1. Outliers are seen on the higher values \n2. Customers are planning to run more than 180 miles per week\n\n","d858721f":"### Analysis of Miles based on Marital Status","640af54e":"### Understand the structure of Data:","7c64e60e":"**Observations:** \n\n1. TM195 is the most sold model\n2. TM798 is the least sold model","720ea84b":"**Observations:**\n\n1. A total of 60 customers purchased TM498 model\n2. Average age of customer is 28.9 (Median: 26) (Range: 19-48)\n3. Data is right skewed.\n4. Average number of years of Education for customers is 15 (Median: 16)\n5. Customer wants use the treadmill at least 3 times per week\n6. Customers are expected to run is 60 miles per week (Median: 85)\n7. Average income is USD 46,000 (Median: USD 49,459)","6a4e26aa":"#### Describe the numerical columns in the dataset","a95eaac6":"**Observations:**\n\n1. There are 6 columns of integer type\n2. There are 3 objects of string type\n3. The dataset is of approximately 12.8 kb in size\n4. There are 180 rows\n","013cccc3":"#### Understand data for Product Code TM195","7f4cd141":"**Dataset Information** :\n\nCardioGoodFitness.csv: The csv contains data related to customers who have purchased different model from Cardio Good Fitness  :\n- Product - the model no. of the treadmill\n- Age - in no of years, of the customer\n- Gender - of the customer\n- Education - in no. of years, of the customer\n- Marital Status - of the customer\n- Usage - Avg. # times the customer wants to use the treadmill every week\n- Fitness - Self rated fitness score of the customer (5 - very fit, 1 - very unfit)\n- Income - of the customer\n- Miles- expected to run\n\n**Objective**\n- Identify differences between customers of each product\n- Explore relationships between the difference attributes of customers","3c445e15":"## Recommendations:\n\n1. TM195 and TM498 are popular with customers in USD 45,000 and USD 60,0000 income range and can be promoted as affordable models for these income groups\n2. TM798 should be branded as Premium Model and marketed among high income groups and specific customer categories. Promotional programs can be run for upgrades from other models.\n3. Rewards programs can be launched to promote per week of usage. Gamification based on points can also be introduced, with weekly leader boards.\n4. Special promotions to be run to target Female Customers, for instance:\n    1. Discounts on Women's Day and similar celebrated ocassions\n    2. Purchase offers using Credit Card or Bank Reward points\n    3. Free additional gifts and hampers from partners\n5. Market research can be conducted to check the feasibility of attracting customers outside the age range of 18-35.","a4e5f6b3":"**Observations:**\n\n1. Number of male customers purchasing treadmill is more than Female Customers\n2. TM798 is the least popular model of treadmill in Female Customers\n3. TM195 is equally preferred model of treadmill in both male and Female Customers","85d4582d":" **Observations:** There are no duplicate values in the dataset","ddd59e13":"### Analysis based on Gender","d84c4b1e":"**Observations:**\n\n1. TM798 leads all charts across Customer Segments\n2. Single Female Customers have purchased more of TM195 and TM498 models compared to Single Male Customers\n3. Single Male Customers are more than Single Female Customers \n4. Partnered Female Customers are more than Partnered Male Customers","bd909d76":"Observations:\n\nPartnered Customers plan to run more miles, when compared to Single Customers","2bd1d9c7":"#### Backup data before manipulation","3620d980":"#### Examine the last 5 rows of the data","96c5b5d1":"### Analysis based on Income","17fcc73d":"**Observations:**\n\nIncome increases with the age, depicting positive correlation.","47eea9b4":"#### Understand data for Product Code TM498","f409f8ef":"#### Describe all columns of the dataset","58a71409":"### Analysis based on Usage","b0d27ab6":"#### Pairplot of all numerical values using KDE","5b3d6f7a":"#### Count based on Marital Status","8d33fcc7":"#### Check the object \/ data types of data in dataframe","59cddff3":"#### Identify the column names in dataset","19eb0e5d":"Observations:\n\nPartnered Customers have higher income range, when compared to Single Customers","daeb3d5c":"### Analysis based on Marital Status","ba347fc9":"### Analysis of Income based on Gender","bd342a49":"**Observations:**\n\nMale Customers plan to run more miles, when compared to Female Customers","3c169cb1":"#### Average\u00a0age\u00a0for\u00a0each\u00a0model","603f39cc":"**Observations:**\n\n1. A total of 40 customers purchased TM798 model\n2. Average age of customer is 29 (Median: 27) (Range: 22-48)\n3. Average number of years of Education for customers is 17 (Median: 18)\n4. Customer wants to use the treadmill at least 4-5 times per week\n5. Customers are expected to run are 166 miles per week (Median: 160)\n6. Average income is USD 75,000 (Median: USD 76,000)","ff7af586":"### Analysis Based on Age","d6e06e9b":"#### Average\u00a0of\u00a0number\u00a0of\u00a0years\u00a0of\u00a0education\u00a0for\u00a0each\u00a0model","6cfab2e2":"Observations:\n\nMale Customers show higher usage per week, when compared to Female Customers","a990d1b3":"## Conclusion (Important Observations):\n\n1. TM195 is most sold model, accounting for 44.44% of total sales.\n2. 57.78% of Customers are Male Customers, which is more than the Female Customers.\n3. Partnered customers account for 59.44% of sales.\n4. Most customers are between 22 to 26 years of age.\n5. TM798 is most preferred by customers with higher income range.","198829de":"**Observations:**\n\n1. Most customers are in the age range of 22 - 32\n2. Further classification reveals that most customers are of ages between 24 and 26 years, followed by customers from age group 22 and 24 years"}}