{"cell_type":{"d7d77e8b":"code","a5dba68d":"code","e1d56a83":"code","4eeb6b1a":"code","ef269171":"code","55862c3a":"code","26d1dfd6":"code","55d13a23":"code","50a62f83":"code","5f229dd8":"code","7d3eca0c":"code","f137e24e":"code","dc97f592":"code","58f14394":"code","a7d2e066":"code","96cbdcf6":"code","106cb4c6":"code","f7e44406":"code","89a1c8aa":"code","9a54d198":"code","9d27f09f":"code","3dde62d1":"code","d4e91764":"code","6d84d2c9":"code","928d37cf":"code","da82a85f":"code","452dd5f6":"code","38e887d3":"code","b32f302e":"code","71f5e239":"code","88152e98":"code","16bcf8ef":"code","2f2a8b52":"code","f6eb0a8b":"code","b611f9b7":"code","c7c24d86":"code","944f778d":"code","ff2fd2af":"code","ffa0da58":"code","cd7399c0":"code","0268a1a1":"code","fb63fe1c":"code","150d6b62":"code","1500211c":"code","6f7e0e54":"code","640e6d1a":"code","363debf9":"code","6a351177":"code","005e84ce":"code","8f3b5f75":"code","b4f8f5b8":"markdown"},"source":{"d7d77e8b":"import pandas as pd\nimport numpy as np\nimport seaborn as sns\nimport matplotlib.pyplot as plt","a5dba68d":"train = pd.read_csv('..\/input\/house-prices-advanced-regression-techniques\/train.csv')\ntest = pd.read_csv('..\/input\/house-prices-advanced-regression-techniques\/test.csv')","e1d56a83":"train.shape","4eeb6b1a":"train.head()","ef269171":"abs(train.corr()['SalePrice']).nlargest(10)","55862c3a":"(train)","26d1dfd6":"sns.distplot(train['SalePrice'])","55d13a23":"train['SalePrice'] = np.log1p(train['SalePrice'])","50a62f83":"n = train.shape[0]\nfor col in train.columns:\n    miss = sum(train[col].isnull())*100.0\/n\n    if miss > 80.0:\n        print('{}: {:0.2f}%'.format(col, miss))","5f229dd8":"train.drop(['PoolQC', 'MiscFeature', 'Alley','Fence'], axis = 1, inplace = True)\ntest.drop(['PoolQC', 'MiscFeature', 'Alley','Fence'], axis = 1, inplace = True)","7d3eca0c":"train.corr()['GarageArea']['GarageCars']","f137e24e":"train.corr()['GarageArea']['SalePrice']","dc97f592":"train.corr()['GarageCars']['SalePrice']","58f14394":"train.drop(['GarageArea'], axis = 1, inplace = True)\ntest.drop(['GarageArea'], axis = 1, inplace = True)","a7d2e066":"c = 'OverallQual'\ntrain.corr()[c][abs(train.corr()[c]) > 0.65]","96cbdcf6":"c = 'GarageCars'\ntrain.corr()[c][abs(train.corr()[c]) > 0.65]","106cb4c6":"c = 'GrLivArea'\ntrain.corr()[c][abs(train.corr()[c]) > 0.65]","f7e44406":"plt.scatter(train['GrLivArea'], train['SalePrice'])\nplt.xlabel('GrLivArea')\nplt.ylabel('SalePrice')","89a1c8aa":"train = train[train[\"GrLivArea\"] < 4000]","9a54d198":"c = 'TotalBsmtSF'\ntrain.corr()[c][abs(train.corr()[c]) > 0.65]","9d27f09f":"plt.scatter(train['TotalBsmtSF'], train['SalePrice'])\nplt.xlabel('TotalBsmtSF')\nplt.ylabel('SalePrice')","3dde62d1":"train.drop(['2ndFlrSF', 'TotRmsAbvGrd', '1stFlrSF'], axis = 1, inplace = True)\ntest.drop(['2ndFlrSF', 'TotRmsAbvGrd', '1stFlrSF'], axis = 1, inplace = True)","d4e91764":"abs(train.corr()['SalePrice']).nsmallest(10)","6d84d2c9":"train.drop(['BsmtFinSF2', 'BsmtHalfBath', 'MiscVal', 'LowQualFinSF', 'YrSold', '3SsnPorch', 'MoSold', 'OverallCond', 'MSSubClass'], axis = 1, inplace = True)\ntest.drop(['BsmtFinSF2', 'BsmtHalfBath', 'MiscVal', 'LowQualFinSF', 'YrSold', '3SsnPorch', 'MoSold', 'OverallCond', 'MSSubClass'], axis = 1, inplace = True)","928d37cf":"train.shape","da82a85f":"abs(train.corr()['SalePrice']).nsmallest(10)","452dd5f6":"train.drop(['PoolArea', 'ScreenPorch', 'EnclosedPorch', 'KitchenAbvGr', 'BedroomAbvGr', 'BsmtUnfSF', 'BsmtFullBath', 'LotArea', 'HalfBath'], axis = 1, inplace = True)\ntest.drop(['PoolArea', 'ScreenPorch', 'EnclosedPorch', 'KitchenAbvGr', 'BedroomAbvGr', 'BsmtUnfSF', 'BsmtFullBath', 'LotArea', 'HalfBath'], axis = 1, inplace = True)","38e887d3":"train.shape","b32f302e":"train.head()","71f5e239":"def fill_missing_data(df):\n    data = df.copy()\n    cat = []\n    for c,dtype in data.dtypes.items():\n        if dtype == 'object':\n            cat.append(c)\n    # Fill 'None' for the Categorical attribute\n    data[cat] = data[cat].fillna('None')\n    \n    for c in data.columns:\n        if c not in cat:\n            data[c] = data[c].fillna(0) #Fill 0 for the Numeric attribute\n    return data","88152e98":"train = fill_missing_data(train)\ntest = fill_missing_data(test)","16bcf8ef":"train.columns","2f2a8b52":"def feature_engineering(df):\n    data = df.copy()\n    \n    feature = {\n        'categorical':{\n            'MSZoning': ['RL', 'RM', 'C (all)', 'FV', 'RH'],\n            'LandContour': ['Lvl', 'Bnk', 'Low', 'HLS'],\n            'LotConfig': ['Inside', 'FR2', 'Corner', 'CulDSac', 'FR3'],\n            'LandSlope': ['Gtl', 'Mod', 'Sev'],\n            'Neighborhood': ['Blmngtn', 'Blueste', 'BrDale', 'BrkSide', 'ClearCr', 'CollgCr', 'Crawfor', 'Edwards', 'Gilbert', 'IDOTRR', 'MeadowV', 'Mitchel',\n                            'Names', 'NoRidge', 'NPkVill', 'NridgHt', 'NWAmes', 'OldTown', 'SWISU', 'Sawyer', 'SawyerW', 'Somerst', 'StoneBr', 'Timber', 'Veenker'],\n            'Condition1': ['Artery', 'Feedr', 'Norm', 'RRNn', 'RRAn', 'PosN', 'PosA', 'RRNe', 'RRAe'],\n            'Condition2': ['Artery', 'Feedr', 'Norm', 'RRNn', 'RRAn', 'PosN', 'PosA', 'RRNe', 'RRAe'],\n            'BldgType': ['1Fam', '2FmCon', 'Duplx', 'TwnhsE', 'TwnhsI'],\n            'HouseStyle': ['1Story', '1.5Fin', '1.5Unf', '2Story', '2.5Fin', '2.5Unf', 'SFoyer', 'SLvl'],\n            'RoofStyle': ['Flat', 'Gable', 'Gambrel', 'Hip', 'Mansard', 'Shed'],\n            'RoofMatl': ['ClyTile', 'CompShg', 'Membran', 'Metal', 'Roll', 'Tar&Grv', 'WdShake', 'WdShngl'],\n            'Exterior1st': ['AsbShng', 'AsphShn', 'BrkComm', 'BrkFace', 'CBlock', 'CemntBd', 'HdBoard', 'ImStucc', 'MetalSd', 'Other', 'Plywood', 'PreCast', 'Stone', 'Stucco',\n                           'VinylSd', 'Wd Sdng', 'WdShing'],\n             'Exterior2nd': ['AsbShng', 'AsphShn', 'BrkComm', 'BrkFace', 'CBlock', 'CemntBd', 'HdBoard', 'ImStucc', 'MetalSd', 'Other', 'Plywood', 'PreCast', 'Stone', 'Stucco',\n                           'VinylSd', 'Wd Sdng', 'WdShing'],\n            'MasVnrType': ['BrkCmn', 'BrkFace', 'CBlock', 'None', 'Stone'],\n            'Foundation': ['BrkTil', 'CBlock', 'PConc', 'Slab', 'Stone', 'Wood'],\n            'Heating': ['Floor', 'GasA', 'GasW', 'Grav', 'OthW', 'Wall'],\n            'Electrical': ['SBrkr', 'FuseA', 'FuseF', 'FuseP', 'Mix'],\n            'Functional': ['Typ', 'Min1', 'Min2', 'Mod', 'Maj1', 'Maj2', 'Sev', 'Sal'],\n            'GarageType': ['2Types', 'Attchd', 'Basment', 'BuiltIn', 'CarPort', 'Detchd', 'None'],\n            'GarageFinish': ['Fin', 'RFn', 'Unf', 'None'],\n            'PavedDrive': ['Y', 'P', 'N'],\n            'MiscFeature': ['Elev', 'Gar2', 'Othr', 'Shed', 'TenC', 'None'],\n            'MoSold': ['1', '2', '3', '4', '5', '6', '7', '8', '9', '10', '11', '12'],\n            'YrSold': ['2006', '2007', '2008', '2009', '2010'],\n            'SaleType': ['WD', 'CWD', 'VWD', 'New', 'COD', 'Con', 'ConLw', 'ConLI', 'ConLD', 'Oth'],\n            'SaleCondition': ['Normal', 'Abnorml', 'AdjLand', 'Alloca', 'Family', 'Partial']\n        },\n        'binary': {\n            'Street': ['Pave', 'Grvl'],\n            'CentralAir': ['Y', 'N']          \n        },\n        'ordinal': {\n            'LotShape': ['None', 'IR3', 'IR2', 'IR1', 'Reg'],\n            'Utilities': ['None', 'NoSeWa', 'NoSewr', 'AllPub'],\n            'LandSlope': ['None', 'Sev', 'Mod', 'Gtl'],\n            'ExterQual': ['None', 'Po', 'Fa', 'TA', 'Gd', 'Ex'],\n            'ExterCond': ['None', 'Po', 'Fa', 'TA', 'Gd', 'Ex'],\n            'BsmtQual': ['None', 'Po', 'Fa', 'TA', 'Gd', 'Ex'],\n            'BsmtCond': ['None', 'Po', 'Fa', 'TA', 'Gd', 'Ex'],\n            'BsmtExposure': ['None', 'No', 'Mn', 'Av', 'Gd'],\n            'BsmtFinType1': ['None', 'Unf', 'LwQ', 'Rec', 'BLQ', 'ALQ', 'GLQ'],\n            'BsmtFinType2': ['None', 'Unf', 'LwQ', 'Rec', 'BLQ', 'ALQ', 'GLQ'],\n            'HeatingQC': ['None', 'Po', 'Fa', 'TA', 'Gd', 'Ex'],\n            'KitchenQual': ['None', 'Po', 'Fa', 'TA', 'Gd', 'Ex'],\n            'FireplaceQu': ['None', 'Po', 'Fa', 'TA', 'Gd', 'Ex'],\n            'GarageQual': ['None', 'Po', 'Fa', 'TA', 'Gd', 'Ex'],\n            'GarageCond': ['None', 'Po', 'Fa', 'TA', 'Gd', 'Ex']\n        },\n    }\n    \n    selected = []\n    for c in data.columns:\n        if c in feature['binary']: # Convert the binary attributes to 0\/1\n            default_value = feature['binary'][c][0]\n            feature_name = c + \"_is_\" + default_value\n            selected.append(feature_name)\n            data[feature_name] = data[c].apply(lambda x: int(x == default_value))\n        elif c in feature['categorical']:\n            values = feature['categorical'][c]\n            for val in values:\n                try:\n                    new_name = \"{}_{}\".format(c, val)\n                    selected.append(new_name)\n                    data[new_name] = data[c].apply(lambda x: int(x == val))\n                except Exception as err:\n                    print(\"One-hot encoding for {}_{}. Error: {}\".format(c, val, err))\n        elif c in feature['ordinal']: # Convert the Ordinal attributes to a number\n            new_name = c + \"_ordinal\"\n            selected.append(new_name)\n            data[new_name] = data[c].apply(lambda x: int(feature['ordinal'][c].index(x)))\n        else: \n            selected.append(c)\n            \n    return data[selected]","f6eb0a8b":"train = feature_engineering(train)\ntest = feature_engineering(test)","b611f9b7":"train","c7c24d86":"for col in train.columns:\n    if any(train[col]) == False:\n        train.drop([col], axis = 1, inplace = True)\n        test.drop([col], axis = 1, inplace = True)","944f778d":"X = test['Id']\nY = train['SalePrice']","ff2fd2af":"train.drop(['Id', 'SalePrice'], axis = 1, inplace = True)\ntest.drop(['Id'], axis = 1, inplace = True)","ffa0da58":"from sklearn.preprocessing import StandardScaler\nscaler = StandardScaler()\nscaler.fit(train)\ntrain_a = scaler.transform(train)\ntest_r = scaler.transform(test)","cd7399c0":"from sklearn.model_selection import train_test_split\nX_train, X_test, Y_train, Y_test = train_test_split(train_a, Y, test_size = 0.10, random_state = 1)\nX_test, X_val, Y_test, Y_val = train_test_split(X_test, Y_test, test_size = 0.5, random_state = 123)","0268a1a1":"from sklearn.metrics import mean_squared_error\npar = {\n    \"max_depth\": 3, \n    \"n_estimators\": 20000, \n    \"learning_rate\": 0.02, \n    \"subsample\": 0.5,\n    \"colsample_bytree\": 1,  \n    \"min_child_weight\": 1.5,\n    \"reg_alpha\": 0.75,\n    \"reg_lambda\": 0.4,\n    \"seed\": 42\n}","fb63fe1c":"#XGB Regressor:\nimport xgboost\nxgb = xgboost.XGBRegressor(**par)\npar_fit = {\n    \"eval_metric\": \"rmse\",\n    \"early_stopping_rounds\": 650,\n    \"verbose\": 200,\n    \"eval_set\": [(X_val, Y_val)]\n}\nxgb.fit(X_train, Y_train, **par_fit)\npred_xgb = xgb.predict(X_test)\nmean_squared_error(Y_test, pred_xgb, squared = False)","150d6b62":"#Lasso Regression:\nfrom sklearn.linear_model import Lasso\nLasso = Lasso(alpha=0.0007)\nLasso.fit(X_train, Y_train)\npred_Lasso = Lasso.predict(X_test)\nmean_squared_error(Y_test, pred_Lasso, squared = False)","1500211c":"#Nearest Neighbors:\nfrom sklearn.neighbors import KNeighborsRegressor\nKNR = KNeighborsRegressor()\nKNR.fit(X_train, Y_train)\npred_KNR = KNR.predict(X_test)\nmean_squared_error(Y_test, pred_KNR, squared = False)","6f7e0e54":"from sklearn.tree import DecisionTreeRegressor\ntree = DecisionTreeRegressor(random_state = 0, min_samples_split = 2, max_depth = 6)  \ntree.fit(X_train, Y_train)\npred_tree = tree.predict(X_test)\nmean_squared_error(Y_test, pred_tree, squared = False)","640e6d1a":"#Random Forest:\nfrom sklearn.ensemble import RandomForestRegressor\nrf = RandomForestRegressor(n_estimators = 550)\nrf.fit(X_train, Y_train)\npred_rf = rf.predict(X_test)\nmean_squared_error(Y_test, pred_rf, squared = False)","363debf9":"#Gradient Boosting Regressor:\nfrom sklearn.ensemble import GradientBoostingRegressor\ngb = GradientBoostingRegressor(\n    max_depth = 5,\n    n_estimators = 2000,\n    learning_rate = 0.25\n)\ngb.fit(X_train, Y_train)\npred_gb = gb.predict(X_test)\nmean_squared_error(Y_test, pred_gb, squared = False)","6a351177":"pred = xgb.predict(test_r)\npred = np.exp(pred)","005e84ce":"sub = pd.DataFrame({'Id': X, 'SalePrice': pred})\nsub.head()","8f3b5f75":"sub.to_csv('submission.csv', index = False)","b4f8f5b8":"#   Let's import the libraries:"}}