{"cell_type":{"cc11d90a":"code","a9c0ef88":"code","4b49f0f1":"code","0a18d7d4":"code","0e0602ca":"code","72b35e70":"code","f95a7bd9":"code","f0d36fbd":"code","5f0dc01b":"code","73358deb":"code","0a0b4343":"code","73c1e1f1":"code","8dc2de56":"code","73c4b0fe":"code","d80a10bb":"code","9cbb4790":"code","24feeb5a":"code","38c4ee8f":"code","09660840":"code","2fbee0b4":"code","c4274a27":"code","dab2c356":"code","645087d7":"code","947e5322":"code","4dd157af":"code","2cc3065c":"code","a4d5c3dd":"code","5acb1ba3":"code","6a1e957c":"code","f0e15844":"code","93e7b5a2":"code","a97b95fe":"code","122f0ab6":"code","31630f1b":"code","68c70b4f":"code","e416ed59":"code","e39978d4":"code","d43cfb9d":"code","dba6163a":"code","d3920bc6":"code","2b44c1f7":"code","92c46042":"code","4e5591d0":"code","2aeb997a":"code","a386915f":"code","ecaf7a87":"code","eac4ff7d":"code","0bbd1e00":"code","2f71a8d7":"code","daf4236b":"code","33e69463":"code","553d170e":"code","a5430f49":"code","83c42764":"code","46166eeb":"code","41b45e8e":"markdown","2069326e":"markdown","e539619a":"markdown","26962b78":"markdown","dec09182":"markdown","30e8bb87":"markdown","50529c1a":"markdown","60849c98":"markdown","5a942a36":"markdown","64bcd835":"markdown","b7176d51":"markdown","00d312ea":"markdown","454a5f17":"markdown","48d7d5db":"markdown","22cddecf":"markdown","948939e7":"markdown","d440e288":"markdown","3081db1e":"markdown","25884c9c":"markdown"},"source":{"cc11d90a":"# This Python 3 environment comes with many helpful analytics libraries installed\n# It is defined by the kaggle\/python Docker image: https:\/\/github.com\/kaggle\/docker-python\n# For example, here's several helpful packages to load\n\nimport numpy as np # linear algebra\nimport pandas as pd # data processing, CSV file I\/O (e.g. pd.read_csv)\n\n# Input data files are available in the read-only \"..\/input\/\" directory\n# For example, running this (by clicking run or pressing Shift+Enter) will list all files under the input directory\nimport matplotlib.pyplot as plt\nimport seaborn as sns\n\n%matplotlib inline\n\nimport os\nfor dirname, _, filenames in os.walk('\/kaggle\/input'):\n    for filename in filenames:\n        print(os.path.join(dirname, filename))\n\n# You can write up to 5GB to the current directory (\/kaggle\/working\/) that gets preserved as output when you create a version using \"Save & Run All\" \n# You can also write temporary files to \/kaggle\/temp\/, but they won't be saved outside of the current session","a9c0ef88":"df = pd.read_csv(\"..\/input\/google-play-store-apps\/googleplaystore.csv\")\ndf.head(3)","4b49f0f1":"df.columns","0a18d7d4":"df.info()\ndf.shape","0e0602ca":"def missing_value_of_data(df):\n    total=df.isnull().sum().sort_values(ascending=False)\n    percentage=round(total\/df.shape[0]*100,2)\n    return pd.concat([total,percentage],axis=1,keys=['Total','Percentage'])\n\n\nmissing_value_of_data(df)","72b35e70":"df[\"App\"].nunique()","f95a7bd9":"df[\"App\"].value_counts()","f0d36fbd":"df[df[\"App\"] == \"ROBLOX\"]","5f0dc01b":"df.drop_duplicates(subset = \"App\", inplace = True)","73358deb":"df[\"App\"].value_counts()","0a0b4343":"df.shape","73c1e1f1":"df[\"Category\"].value_counts()","8dc2de56":"df[df[\"Category\"] == \"1.9\"]","73c4b0fe":"df.at[10472, \"Category\"] = \"PHOTOGRAPHY\"\ndf.at[10472, \"Installs\"] = \"1,000,000+\"\ndf.at[10472, \"Price\"] = \"0\"\ndf.at[10472, \"Last Updated\"] = \"July 20, 2018\"\ndf.at[10472, \"Current Ver\"] = \"1.0.19\"\ndf.at[10472, \"Android Ver\"] = \"4.0 and up\"","d80a10bb":"df[df[\"App\"] == \"Life Made WI-Fi Touchscreen Photo Frame\"]","9cbb4790":"df[\"Category\"].value_counts()","24feeb5a":"df[\"Rating\"].value_counts()","38c4ee8f":"df[df[\"Rating\"] == 19.0]","09660840":"average_rating = df[\"Rating\"].mean()\ndf.at[10472, \"Rating\"] = round(average_rating, 1)","2fbee0b4":"df.loc[df[\"App\"] == \"Life Made WI-Fi Touchscreen Photo Frame\"]","c4274a27":"df[\"Rating\"].isnull().sum()","dab2c356":"df[\"Rating\"] = df.groupby(\"Category\").transform(lambda x: x.fillna(round(x.mean(),1)))","645087d7":"df[\"Reviews\"].value_counts()","947e5322":"df[\"Type\"].value_counts()","4dd157af":"df.loc[df[\"Type\"] == \"0\"]","2cc3065c":"df.at[10472, \"Type\"] = \"Free\"\ndf[\"Type\"].value_counts()","a4d5c3dd":"df[\"Type\"].isnull().sum()","5acb1ba3":"df[df[\"Type\"].isnull() == True]","6a1e957c":"df.at[9148, \"Type\"] = \"Free\"","f0e15844":"labels = df[\"Type\"].value_counts().index\nsizes = df[\"Type\"].value_counts()\nexplode = (0, 0.1)\n\nfig1, ax1 = plt.subplots()\nax1.pie(sizes, explode=explode, labels=labels, autopct='%1.1f%%',\n        shadow=True, startangle=30)\nax1.axis('equal')  # Equal aspect ratio ensures that pie is drawn as a circle.\n\nplt.title(\"Percentage of Free and Paid Apps\")\nplt.show()","93e7b5a2":"df[\"Size\"].value_counts()","a97b95fe":"df[\"Size\"].isnull().sum()","122f0ab6":"df[\"Size\"].unique()","31630f1b":"def size_convert(i):\n    if \"M\" in i:\n        return float(i[:-1]) * 1000\n    elif \"K\" in i:\n        return float(i[:-1])\n    else:\n        return i\ndf[\"Size\"] = df[\"Size\"].apply(size_convert)","68c70b4f":"df[\"Installs\"].isnull().sum()","e416ed59":"df[\"Installs\"].unique()","e39978d4":"df[\"Installs\"] = df[\"Installs\"].apply(lambda x: x.replace(',',''))\ndf[\"Installs\"] = df[\"Installs\"].apply(lambda x: x.replace('+',''))\ndf[\"Installs\"] = df[\"Installs\"].apply(lambda x: int(x))","d43cfb9d":"sorted_value = sorted(list(df[\"Installs\"].unique()))\ndf[\"Installs\"].replace(sorted_value,range(0,len(sorted_value),1), inplace = True )\nplt.figure(figsize = (10,10))\nsns.regplot(x = \"Installs\", y = \"Rating\", color = 'r',data=df);\nplt.title('Rating vs Installs',size = 20)","dba6163a":"df.info()","d3920bc6":"df[\"Content Rating\"].isnull().sum()","2b44c1f7":"df[\"Content Rating\"].unique()","92c46042":"df[df[\"Content Rating\"].isnull() == True]","4e5591d0":"df.at[10472, \"Content Rating\"] = \"Everyone\"","2aeb997a":"df[\"Genres\"].unique()","a386915f":"df.loc[df[\"Genres\"] == \"February 11, 2018\"]","ecaf7a87":"df.at[10472, \"Genres\"] = \"Photography\"","eac4ff7d":"df[\"Current Ver\"].nunique()","0bbd1e00":"df[\"Current Ver\"].isnull().sum()","2f71a8d7":"df[\"Current Ver\"].fillna(\"1.0\", inplace = True)","daf4236b":"df[\"Android Ver\"].unique()","33e69463":"df[\"Android Ver\"].value_counts()","553d170e":"def and_version(i):\n    if str(i) == \"4.4W and up\":\n        return \"4.4 and up\"\n    elif \"-\" in str(i):\n        return str(i.split(\" \")[0]) + \" and up\"\n    else:\n        return i\n\ndf[\"Android Ver\"] = df[\"Android Ver\"].apply(and_version)","a5430f49":"df[\"Android Ver\"].value_counts()","83c42764":"df.loc[df[\"Android Ver\"].isnull() == True]","46166eeb":"df.at[10472, \"Price\"] = \"0\"\ndf.at[10472, \"Last Updated\"] = \"July 20, 2018\"\ndf.at[10472, \"Current Ver\"] = \"1.0.19\"\ndf.at[10472, \"Android Ver\"] = \"4.0 and up\"\ndf[\"Android Ver\"].fillna(\"4.0 and up\", inplace = True)\ndf.info()","41b45e8e":"Values in string format, so they should be converted into integers. Thus, \"+\" and \",\" should be removed first, then convert into integers.","2069326e":"# <a id=size>Size<\/a>","e539619a":"# <a id=content_rating>Content Rating<\/a>","26962b78":"# <a id=type>Type<\/a>","dec09182":"# <a id=rating>Rating<\/a>","30e8bb87":"# <a id=installs>Installs<\/a>","50529c1a":"# <a id=reviews>Reviews<\/a>","60849c98":"## Thank you and good luck everyone! Please support, comment and vote :)","5a942a36":"Size of apps contains prefixes for Kilo and Mega. They should be converted into float and kept in same unit.\n","64bcd835":"# <a id=app>App<\/a>","b7176d51":"# <a id=cat>Category<\/a>","00d312ea":"In order to have a clean result, all data should be like \"4.0 and up\", instead of this.\n\n4.0.3 - 7.1.1 2 5.0 - 8.0 2 7.0 - 7.1.1 1 4.1 - 7.1.1 1 5.0 - 7.1.1 1 5.0 - 6.0 1 2.2 - 7.1.1 1","454a5f17":"# <a id=genres>Genres<\/a>","48d7d5db":"So, data in this row is not correct, I change it below.","22cddecf":"# <a id=android_version>Android Version<\/a>","948939e7":"# <a id=current_version>Current Version<\/a>","d440e288":"Obviously, one of the cells contains an unexpected category which is \"1.9\".","3081db1e":"Let's find the nan, now. Then, change it to \"Free\", becuase most of the apps are free.\n","25884c9c":"Each column will be explored individually.\n1. [App](#app)\n2. [Category](#cat)\n3. [Rating](#rating)\n4. [Reviews](#reviews)\n5. [Type](#type)\n6. [Size](#size)\n7. [Installs](#installs)\n8. [Content Rating](#content_rating)\n9. [Genres](#genres)\n10. [Current Version](#current_version)\n11. [Android Version](#android_version)"}}